postgkyl/__init__.py
postgkyl/pgkyl.py
postgkyl/commands/__init__.py
postgkyl/commands/agyro.py
postgkyl/commands/animate.py
postgkyl/commands/bparrotate.py
postgkyl/commands/bperprotate.py
postgkyl/commands/collect.py
postgkyl/commands/current.py
postgkyl/commands/data_space.py
postgkyl/commands/differentiate.py
postgkyl/commands/energetics.py
postgkyl/commands/euler.py
postgkyl/commands/ev.py
postgkyl/commands/ev_cmd.py
postgkyl/commands/extractinput.py
postgkyl/commands/fft.py
postgkyl/commands/gkyl_pkpm.py
postgkyl/commands/grid.py
postgkyl/commands/growth.py
postgkyl/commands/info.py
postgkyl/commands/integrate.py
postgkyl/commands/interpolate.py
postgkyl/commands/laguerre_compose.py
postgkyl/commands/listoutputs.py
postgkyl/commands/load.py
postgkyl/commands/magsq.py
postgkyl/commands/mask.py
postgkyl/commands/mhd.py
postgkyl/commands/parrotate.py
postgkyl/commands/perprotate.py
postgkyl/commands/plot.py
postgkyl/commands/pr.py
postgkyl/commands/relchange.py
postgkyl/commands/select.py
postgkyl/commands/status.py
postgkyl/commands/style.py
postgkyl/commands/temp.py
postgkyl/commands/tenmoment.py
postgkyl/commands/trajectory.py
postgkyl/commands/transform_frame.py
postgkyl/commands/val2coord.py
postgkyl/commands/velocity.py
postgkyl/commands/write.py
postgkyl/commands/old/cglpressure.py
postgkyl/commands/old/recovery.py
postgkyl/data/__init__.py
postgkyl/data/computeDerivativeMatrices.py
postgkyl/data/computeInterpolationMatrices.py
postgkyl/data/dg.py
postgkyl/data/flash_h5_reader.py
postgkyl/data/gdata.py
postgkyl/data/gkyl_adios_reader.py
postgkyl/data/gkyl_h5_reader.py
postgkyl/data/gkyl_reader.py
postgkyl/data/idx_parser.py
postgkyl/data/select.py
postgkyl/data/old/recovData.py
postgkyl/modalDG/__init__.py
postgkyl/modalDG/interpolate.py
postgkyl/modalDG/kernels/__init__.py
postgkyl/modalDG/kernels/expand1d.py
postgkyl/modalDG/kernels/expand2d.py
postgkyl/modalDG/kernels/expand3d.py
postgkyl/modalDG/kernels/expand4d.py
postgkyl/modalDG/kernels/expand5d.py
postgkyl-1.7.6.dist-info/licenses/AUTHORS.md
postgkyl-1.7.6.dist-info/licenses/LICENSE
postgkyl-1.7.6.dist-info/METADATA
postgkyl-1.7.6.dist-info/WHEEL
postgkyl-1.7.6.dist-info/entry_points.txt
postgkyl-1.7.6.dist-info/top_level.txt
postgkyl-1.7.6.dist-info/RECORD
