Metadata-Version: 2.4
Name: postgkyl
Version: 1.7.6
Summary: Python library and command-line tool for postprocessing (not only) Gkeyll data
Author-email: Ammar Hakim <a.hakim@pppl.gov>, Petr Cagas <p.cagas@hzdr.de>
Maintainer-email: Petr Cagas <p.cagas@hzdr.de>
License: MIT License
Project-URL: Documentation, https://gkeyll.readthedocs.io/
Project-URL: Repository, https://github.com/ammarhakim/postgkyl
Project-URL: Bug Tracker, https://github.com/ammarhakim/postgkyl/issues
Keywords: plasma,Gkeyll
Classifier: Development Status :: 4 - Beta
Classifier: Intended Audience :: Developers
Classifier: Intended Audience :: Science/Research
Classifier: License :: OSI Approved :: MIT License
Classifier: Operating System :: OS Independent
Classifier: Programming Language :: Python
Classifier: Programming Language :: Python :: 3
Classifier: Programming Language :: Python :: 3 :: Only
Classifier: Programming Language :: Python :: 3.11
Classifier: Programming Language :: Python :: 3.12
Classifier: Topic :: Scientific/Engineering
Requires-Python: >=3.10
License-File: LICENSE
License-File: AUTHORS.md
Requires-Dist: click>=8.1.7
Requires-Dist: matplotlib>=3.7.0
Requires-Dist: msgpack>=1.0.3
Requires-Dist: numpy<2,>=1.24.4
Requires-Dist: scipy>=1.10.1
Requires-Dist: sympy>=1.12
Requires-Dist: tables>=3.8.0
Provides-Extra: adios
Requires-Dist: adios2<2.10.0,>=2.9.0; extra == "adios"
Provides-Extra: test
Requires-Dist: pytest>=7.4.0; extra == "test"
Dynamic: license-file
